anythingpassword/__init__.py
anythingpassword/cli.py
anythingpassword/main.py
anythingpassword/passwordlist.py
anythingpassword/tests/__init__.py
anythingpassword/tests/test_anythingpassword.py
anythingpassword-0.2.3.dist-info/METADATA
anythingpassword-0.2.3.dist-info/WHEEL
anythingpassword-0.2.3.dist-info/entry_points.txt
anythingpassword-0.2.3.dist-info/top_level.txt
anythingpassword-0.2.3.dist-info/RECORD
