Metadata-Version: 2.4
Name: anythingpassword
Version: 0.2.3
Summary: This Python application provides a suite of tools for generating, analyzing, encrypting, and managing passwords securely.
Home-page: https://github.com/akinboye/anythingpassword
Author: Akinboye Yusuff
Author-email: mailakinboye@gmail.com
License: MIT
Classifier: Programming Language :: Python :: 3
Classifier: License :: OSI Approved :: MIT License
Classifier: Operating System :: OS Independent
Requires-Python: >=3.8
Requires-Dist: cryptography==44.0.2
Dynamic: author
Dynamic: author-email
Dynamic: classifier
Dynamic: description
Dynamic: description-content-type
Dynamic: home-page
Dynamic: license
Dynamic: requires-dist
Dynamic: requires-python
Dynamic: summary
